{
  "display": {
    "title": {
      "text": "Tired of searching",
      "color": "green"
    },
    "description": {
      "text": "Get Fresh Seeds"
    },
    "icon": {
      "item": "eurekacraft:fresh_seeds"
    },
    "frame": "goal",
    "show_toast": true,
    "announce_to_chat": true,
    "hidden": false,
    "background": "minecraft:textures/gui/advancements/backgrounds/stone.png"
  },
  "criteria": {
    "Seeds": {
      "trigger": "minecraft:inventory_changed",
      "conditions": {
        "items": [
          {
            "items": ["eurekacraft:fresh_seeds"]
          }
        ]
      }
    }
  },
  "requirements": [
    [
      "Seeds"
    ]
  ],
  "rewards": {
    "experience": 50
  },
  "parent": "eurekacraft:root"
}