{
  "display": {
    "title": {
      "text": "Mind the fumes",
      "color": "white"
    },
    "description": {
      "text": "Create a Resin Block using the Ref Table"
    },
    "icon": {
      "item": "eurekacraft:resin_block"
    },
    "frame": "task",
    "show_toast": true,
    "announce_to_chat": true,
    "hidden": false,
    "background": "minecraft:textures/gui/advancements/backgrounds/stone.png"
  },
  "criteria": {
    "Board": {
      "trigger": "eurekacraft:ref_table_trigger",
      "conditions": {
        "machine_output": {
          "items": ["eurekacraft:resin_block"]
        }
      }
    }
  },
  "requirements": [
    [
      "Board"
    ]
  ],
  "rewards": {
    "experience": 50
  },
  "parent": "eurekacraft:ref_table"
}